odoo/addons/partner_invoicing_frequency/README.rst
odoo/addons/partner_invoicing_frequency/__init__.py
odoo/addons/partner_invoicing_frequency/__manifest__.py
odoo/addons/partner_invoicing_frequency/i18n/es.po
odoo/addons/partner_invoicing_frequency/models/__init__.py
odoo/addons/partner_invoicing_frequency/models/account_move.py
odoo/addons/partner_invoicing_frequency/models/partner_invoicing_frequency.py
odoo/addons/partner_invoicing_frequency/models/partner_invoicing_frequency_mixin.py
odoo/addons/partner_invoicing_frequency/models/purchase_order.py
odoo/addons/partner_invoicing_frequency/models/res_partner.py
odoo/addons/partner_invoicing_frequency/models/sale_order.py
odoo/addons/partner_invoicing_frequency/models/stock_picking.py
odoo/addons/partner_invoicing_frequency/security/ir.model.access.csv
odoo/addons/partner_invoicing_frequency/static/description/icon.png
odoo/addons/partner_invoicing_frequency/views/account_move_views.xml
odoo/addons/partner_invoicing_frequency/views/partner_invoicing_frequency_views.xml
odoo/addons/partner_invoicing_frequency/views/purchase_views.xml
odoo/addons/partner_invoicing_frequency/views/res_partner_views.xml
odoo/addons/partner_invoicing_frequency/views/sale_order_views.xml
odoo/addons/partner_invoicing_frequency/views/stock_picking_views.xml
odoo_addon_partner_invoicing_frequency-17.0.1.0.2.dist-info/METADATA
odoo_addon_partner_invoicing_frequency-17.0.1.0.2.dist-info/WHEEL
odoo_addon_partner_invoicing_frequency-17.0.1.0.2.dist-info/top_level.txt
odoo_addon_partner_invoicing_frequency-17.0.1.0.2.dist-info/RECORD
