Metadata-Version: 2.1
Name: odoo-addon-partner_invoicing_frequency
Version: 17.0.1.0.2
Requires-Python: >=3.10
Requires-Dist: odoo>=17.0a,<17.1dev
Summary: Select a invoicing frequency in partners
Home-page: https://github.com/sygel-technology/sy-partner-contact
License: AGPL-3
Author: Sygel
Classifier: Programming Language :: Python
Classifier: Framework :: Odoo
Classifier: Framework :: Odoo :: 17.0
Classifier: License :: OSI Approved :: GNU Affero General Public License v3
